CHANGELOG
LICENSE
MANIFEST.in
README.md
_README.md
__init__.py
setup.cfg
setup.py
test.py
WebPortfolio.egg-info/PKG-INFO
WebPortfolio.egg-info/SOURCES.txt
WebPortfolio.egg-info/dependency_links.txt
WebPortfolio.egg-info/entry_points.txt
WebPortfolio.egg-info/not-zip-safe
WebPortfolio.egg-info/pbr.json
WebPortfolio.egg-info/requires.txt
WebPortfolio.egg-info/top_level.txt
devtest/__init__.py
devtest/manage.py
devtest/run_www.py
devtest/application/__init__.py
devtest/application/config.py
devtest/application/model.py
devtest/application/www/__init__.py
devtest/application/www/views.py
devtest3/manage.py
devtest3/serve_www.py
devtest3/application/__init__.py
devtest3/application/config.py
devtest3/application/model.py
devtest3/application/www/__init__.py
devtest3/application/www/views.py
webportfolio/__about__.py
webportfolio/__about__.pyc
webportfolio/__init__.py
webportfolio/__init__.pyc
webportfolio/cli.py
webportfolio/cli.pyc
webportfolio/core.py
webportfolio/core.pyc
webportfolio/decorators.py
webportfolio/decorators.pyc
webportfolio/ext.py
webportfolio/ext.pyc
webportfolio/jinja2htmlcompress.py
webportfolio/jinja2htmlcompress.pyc
webportfolio/utils.py
webportfolio/utils.pyc
webportfolio/wp_markdown.py
webportfolio/wp_markdown.pyc
webportfolio/app-skel/blank
webportfolio/app-skel/config.py
webportfolio/app-skel/manage.py
webportfolio/app-skel/model.py
webportfolio/app-skel/propel.yml
webportfolio/app-skel/serve.py
webportfolio/app-skel/app/__init__.py
webportfolio/app-skel/app/views.py
webportfolio/app-skel/app/static/assets.yml
webportfolio/app-skel/app/static/css/admin.css
webportfolio/app-skel/app/static/css/style.css
webportfolio/app-skel/app/static/images/blank
webportfolio/app-skel/app/static/js/admin.js
webportfolio/app-skel/app/static/js/app.js
webportfolio/app-skel/app/templates/admin-layout.html
webportfolio/app-skel/app/templates/layout.html
webportfolio/app-skel/app/templates/macros.html
webportfolio/app-skel/app/templates/Account/index.html
webportfolio/app-skel/app/templates/Account/no_login.html
webportfolio/app-skel/app/templates/Account/upload.html
webportfolio/app-skel/app/templates/Admin/_layout.html
webportfolio/app-skel/app/templates/Admin/index.html
webportfolio/app-skel/app/templates/Admin/page_2.html
